token_injectable_docker_builder/__init__.py
token_injectable_docker_builder/py.typed
token_injectable_docker_builder/_jsii/__init__.py
token_injectable_docker_builder/_jsii/token-injectable-docker-builder@1.5.23.jsii.tgz
token_injectable_docker_builder-1.5.23.dist-info/LICENSE
token_injectable_docker_builder-1.5.23.dist-info/METADATA
token_injectable_docker_builder-1.5.23.dist-info/WHEEL
token_injectable_docker_builder-1.5.23.dist-info/top_level.txt
token_injectable_docker_builder-1.5.23.dist-info/RECORD
