Metadata-Version: 2.1
Name: token-injectable-docker-builder
Version: 1.5.23
Summary: The TokenInjectableDockerBuilder is a flexible AWS CDK construct that enables the usage of AWS CDK tokens in the building, pushing, and deployment of Docker images to Amazon Elastic Container Registry (ECR). It leverages AWS CodeBuild and Lambda custom resources.
Home-page: https://github.com/AlexTech314/TokenInjectableDockerBuilder.git
Author: AlexTech314<alest314@gmail.com>
License: MIT
Project-URL: Source, https://github.com/AlexTech314/TokenInjectableDockerBuilder.git
Classifier: Intended Audience :: Developers
Classifier: Operating System :: OS Independent
Classifier: Programming Language :: JavaScript
Classifier: Programming Language :: Python :: 3 :: Only
Classifier: Programming Language :: Python :: 3.9
Classifier: Programming Language :: Python :: 3.10
Classifier: Programming Language :: Python :: 3.11
Classifier: Typing :: Typed
Classifier: Development Status :: 5 - Production/Stable
Classifier: License :: OSI Approved
Requires-Python: ~=3.9
License-File: LICENSE
Requires-Dist: aws-cdk-lib <3.0.0,>=2.173.2
Requires-Dist: constructs <11.0.0,>=10.0.5
Requires-Dist: jsii <2.0.0,>=1.126.0
Requires-Dist: publication >=0.0.3
Requires-Dist: typeguard ==2.13.3
